README.txt
setup.py
collective/__init__.py
collective.blueprint.base.egg-info/PKG-INFO
collective.blueprint.base.egg-info/SOURCES.txt
collective.blueprint.base.egg-info/dependency_links.txt
collective.blueprint.base.egg-info/entry_points.txt
collective.blueprint.base.egg-info/namespace_packages.txt
collective.blueprint.base.egg-info/not-zip-safe
collective.blueprint.base.egg-info/requires.txt
collective.blueprint.base.egg-info/top_level.txt
collective/blueprint/__init__.py
collective/blueprint/base/README.txt
collective/blueprint/base/__init__.py
collective/blueprint/base/blueprint.py
collective/blueprint/base/configure.zcml
collective/blueprint/base/keys.py
collective/blueprint/base/testing.py
collective/blueprint/base/tests.py
collective/blueprint/base/configsource/README.txt
collective/blueprint/base/configsource/__init__.py
collective/blueprint/base/configsource/blueprint.py
collective/blueprint/base/configsource/configure.zcml
collective/blueprint/base/configsource/tests.py
collective/blueprint/base/delete/README.txt
collective/blueprint/base/delete/__init__.py
collective/blueprint/base/delete/blueprint.py
collective/blueprint/base/delete/configure.zcml
collective/blueprint/base/delete/tests.py
collective/blueprint/base/keysplitter/README.txt
collective/blueprint/base/keysplitter/__init__.py
collective/blueprint/base/keysplitter/blueprint.py
collective/blueprint/base/keysplitter/configure.zcml
collective/blueprint/base/keysplitter/tests.py
collective/blueprint/base/recurser/README.txt
collective/blueprint/base/recurser/__init__.py
collective/blueprint/base/recurser/blueprint.py
collective/blueprint/base/recurser/configure.zcml
collective/blueprint/base/recurser/tests.py
docs/HISTORY.txt