Metadata-Version: 1.0
Name: collective.blueprint.base
Version: 1.0
Summary: Some core transmogrifier blueprints and base classes
Home-page: http://pypi.python.org/pypi/collective.blueprint.base
Author: Ross Patterson
Author-email: me@rpatterson.net
License: GPL
Platform: UNKNOWN
Classifier: Programming Language :: Python
Classifier: Topic :: Software Development :: Libraries :: Python Modules
